tomllint/main.py
tomllint-0.3.2.dist-info/licenses/LICENSE
tomllint-0.3.2.dist-info/METADATA
tomllint-0.3.2.dist-info/WHEEL
tomllint-0.3.2.dist-info/entry_points.txt
tomllint-0.3.2.dist-info/top_level.txt
tomllint-0.3.2.dist-info/RECORD
