Metadata-Version: 2.4
Name: tomllint
Version: 0.3.2
Summary: A simple TOML linter.
Author: Will Bradley
License: Creative Commons Legal Code
Project-URL: homepage, https://github.com/wbbradley/tomllint
Project-URL: repository, https://github.com/wbbradley/tomllint
Keywords: toml,lint
Requires-Python: >=3.11
License-File: LICENSE
Dynamic: license-file
